BlueRainHelper/__init__.py
BlueRainHelper/aider_QOL.py
BlueRainHelper/aider_menuBuilder.py
BlueRainHelper/tempCodeRunnerFile.py
bluerainhelper-1.1.1.dist-info/licenses/LICENSE.txt
bluerainhelper-1.1.1.dist-info/METADATA
bluerainhelper-1.1.1.dist-info/WHEEL
bluerainhelper-1.1.1.dist-info/top_level.txt
bluerainhelper-1.1.1.dist-info/RECORD
