Metadata-Version: 2.4
Name: BlueRainHelper
Version: 1.1.1
Summary: A simple CLI menu builder with method chaining
Author-email: Asda1-max <rakhathrd1314@gmail.com>
License: MIT
Project-URL: Homepage, https://github.com/asda1-max
Requires-Python: >=3.8
License-File: LICENSE.txt
Dynamic: license-file
